structlog_asgi/__init__.py
structlog_asgi/config.py
structlog_asgi/testing.py
structlog_asgi/integrations/__init__.py
structlog_asgi/integrations/gunicorn/__init__.py
structlog_asgi/integrations/gunicorn/logger.py
structlog_asgi/integrations/gunicorn/worker.py
structlog_asgi/integrations/uvicorn/__init__.py
structlog_asgi/integrations/uvicorn/worker.py
structlog_asgi-0.0.1.dist-info/LICENSE
structlog_asgi-0.0.1.dist-info/METADATA
structlog_asgi-0.0.1.dist-info/WHEEL
structlog_asgi-0.0.1.dist-info/top_level.txt
structlog_asgi-0.0.1.dist-info/RECORD
